timml/__init__.py
timml/aquifer.py
timml/aquifer_parameters.py
timml/bessel.py
timml/circareasink.py
timml/circinhom.py
timml/constant.py
timml/controlpoints.py
timml/element.py
timml/equation.py
timml/inhomogeneity.py
timml/inhomogeneity1d.py
timml/intlinesink.py
timml/linedoublet.py
timml/linedoublet1d.py
timml/linesink.py
timml/linesink1d.py
timml/model.py
timml/plots.py
timml/stripareasink.py
timml/trace.py
timml/uflow.py
timml/version.py
timml/well.py
timml/besselaesnumba/__init__.py
timml/besselaesnumba/besselaesnumba.py
timml/besselaesnumba/besselaesnumba_old.py
timml-6.7.0.dist-info/licenses/LICENSE
timml-6.7.0.dist-info/METADATA
timml-6.7.0.dist-info/WHEEL
timml-6.7.0.dist-info/top_level.txt
timml-6.7.0.dist-info/RECORD
